bin/hpcbind
bin/nvcc_wrapper
bin/kokkos_launch_compiler
scaluq-0.1.0.dist-info/RECORD
scaluq-0.1.0.dist-info/WHEEL
scaluq-0.1.0.dist-info/METADATA
scaluq-0.1.0.dist-info/licenses/LICENSE
include/eigen3/signature_of_eigen3_matrix_library
include/eigen3/unsupported/Eigen/MatrixFunctions
include/eigen3/unsupported/Eigen/AdolcForward
include/eigen3/unsupported/Eigen/AlignedVector3
include/eigen3/unsupported/Eigen/OpenGLSupport
include/eigen3/unsupported/Eigen/LevenbergMarquardt
include/eigen3/unsupported/Eigen/AutoDiff
include/eigen3/unsupported/Eigen/NumericalDiff
include/eigen3/unsupported/Eigen/NonLinearOptimization
include/eigen3/unsupported/Eigen/ArpackSupport
include/eigen3/unsupported/Eigen/BVH
include/eigen3/unsupported/Eigen/NNLS
include/eigen3/unsupported/Eigen/SpecialFunctions
include/eigen3/unsupported/Eigen/Splines
include/eigen3/unsupported/Eigen/KroneckerProduct
include/eigen3/unsupported/Eigen/IterativeSolvers
include/eigen3/unsupported/Eigen/FFT
include/eigen3/unsupported/Eigen/EulerAngles
include/eigen3/unsupported/Eigen/SparseExtra
include/eigen3/unsupported/Eigen/Polynomials
include/eigen3/unsupported/Eigen/MPRealSupport
include/eigen3/unsupported/Eigen/CXX11/ThreadPool
include/eigen3/unsupported/Eigen/CXX11/TensorSymmetry
include/eigen3/unsupported/Eigen/CXX11/Tensor
include/eigen3/unsupported/Eigen/CXX11/src/util/CXX11Meta.h
include/eigen3/unsupported/Eigen/CXX11/src/util/CXX11Workarounds.h
include/eigen3/unsupported/Eigen/CXX11/src/TensorSymmetry/InternalHeaderCheck.h
include/eigen3/unsupported/Eigen/CXX11/src/TensorSymmetry/DynamicSymmetry.h
include/eigen3/unsupported/Eigen/CXX11/src/TensorSymmetry/StaticSymmetry.h
include/eigen3/unsupported/Eigen/CXX11/src/TensorSymmetry/Symmetry.h
include/eigen3/unsupported/Eigen/CXX11/src/TensorSymmetry/util/TemplateGroupTheory.h
include/eigen3/unsupported/Eigen/CXX11/src/Tensor/TensorRandom.h
include/eigen3/unsupported/Eigen/CXX11/src/Tensor/TensorUInt128.h
include/eigen3/unsupported/Eigen/CXX11/src/Tensor/TensorReductionGpu.h
include/eigen3/unsupported/Eigen/CXX11/src/Tensor/TensorConversion.h
