Metadata-Version: 2.4
Name: scaluq
Version: 0.1.0
Summary: Quantum circuit simulator for research
Author-Email: Qulacs-Osaka <qulacs.osaka@gmail.com>
License-Expression: MIT
License-File: LICENSE
Classifier: Development Status :: 3 - Alpha
Classifier: Environment :: Console
Classifier: Intended Audience :: Science/Research
Classifier: Operating System :: MacOS :: MacOS X
Classifier: Operating System :: Microsoft :: Windows
Classifier: Operating System :: POSIX
Classifier: Programming Language :: Python
Classifier: Topic :: Communications :: Email
Project-URL: homepage, http://www.scaluq.org
Requires-Python: >=3.9
Requires-Dist: numpy>=1.22.0
Requires-Dist: scipy>=1.11.0
Provides-Extra: doc
Requires-Dist: black==24.4.2; extra == "doc"
Requires-Dist: isort==5.13.2; extra == "doc"
Requires-Dist: nanobind==2.0.0; extra == "doc"
Requires-Dist: sphinx==7.3.7; extra == "doc"
Requires-Dist: sphinx-autoapi==3.1.1; extra == "doc"
Requires-Dist: sphinxcontrib-napoleon==0.7; extra == "doc"
Requires-Dist: sphinx_rtd_theme==2.0.0; extra == "doc"
Requires-Dist: sphinx-math-dollar==1.2.1; extra == "doc"
